rrec
